reddit_view
