Metadata-Version: 1.1
Name: reddit-view
Version: 0.0.7b0
Summary: a reddit image collector
Home-page: https://github.com/japrogramer/reddit_view
Author: Jorge Perez
Author-email: japrogramer@gmail.com
License: BSD
Keywords: reddit images imgur links list subreddits
Platform: UNKNOWN
Classifier: Development Status :: 4 - Beta
Classifier: Environment :: Web Environment
Classifier: Intended Audience :: Developers
Classifier: License :: OSI Approved :: BSD License
Classifier: Operating System :: OS Independent
Classifier: Programming Language :: Python
